[
  {
    "time": "2026-07-06T22:20:35Z",
    "busyness": 82,
    "low": 64,
    "high": 100,
    "rush_hour": false,
    "confidence": "medium"
  },
  {
    "time": "2026-07-06T23:20:35Z",
    "busyness": 82,
    "low": 64,
    "high": 100,
    "rush_hour": false,
    "confidence": "medium"
  },
  {
    "time": "2026-07-07T00:20:35Z",
    "busyness": 82,
    "low": 64,
    "high": 100,
    "rush_hour": false,
    "confidence": "medium"
  },
  {
    "time": "2026-07-07T01:20:35Z",
    "busyness": 82,
    "low": 64,
    "high": 100,
    "rush_hour": false,
    "confidence": "medium"
  },
  {
    "time": "2026-07-07T02:20:35Z",
    "busyness": 82,
    "low": 64,
    "high": 100,
    "rush_hour": false,
    "confidence": "medium"
  },
  {
    "time": "2026-07-07T03:20:35Z",
    "busyness": 82,
    "low": 64,
    "high": 100,
    "rush_hour": false,
    "confidence": "medium"
  },
  {
    "time": "2026-07-07T04:20:35Z",
    "busyness": 82,
    "low": 64,
    "high": 100,
    "rush_hour": false,
    "confidence": "medium"
  },
  {
    "time": "2026-07-07T05:20:35Z",
    "busyness": 82,
    "low": 64,
    "high": 100,
    "rush_hour": false,
    "confidence": "medium"
  },
  {
    "time": "2026-07-07T06:20:35Z",
    "busyness": 82,
    "low": 64,
    "high": 100,
    "rush_hour": false,
    "confidence": "medium"
  },
  {
    "time": "2026-07-07T07:20:35Z",
    "busyness": 94,
    "low": 76,
    "high": 100,
    "rush_hour": true,
    "confidence": "medium"
  },
  {
    "time": "2026-07-07T08:20:35Z",
    "busyness": 94,
    "low": 76,
    "high": 100,
    "rush_hour": true,
    "confidence": "medium"
  },
  {
    "time": "2026-07-07T09:20:35Z",
    "busyness": 94,
    "low": 76,
    "high": 100,
    "rush_hour": true,
    "confidence": "medium"
  }
]