[
  {
    "time": "2026-01-24T13:22:13Z",
    "busyness": 69,
    "low": 50,
    "high": 87,
    "rush_hour": false,
    "confidence": "medium"
  },
  {
    "time": "2026-01-24T14:22:13Z",
    "busyness": 69,
    "low": 50,
    "high": 87,
    "rush_hour": false,
    "confidence": "medium"
  },
  {
    "time": "2026-01-24T15:22:13Z",
    "busyness": 69,
    "low": 50,
    "high": 87,
    "rush_hour": false,
    "confidence": "medium"
  },
  {
    "time": "2026-01-24T16:22:13Z",
    "busyness": 81,
    "low": 62,
    "high": 99,
    "rush_hour": true,
    "confidence": "medium"
  },
  {
    "time": "2026-01-24T17:22:13Z",
    "busyness": 81,
    "low": 62,
    "high": 99,
    "rush_hour": true,
    "confidence": "medium"
  },
  {
    "time": "2026-01-24T18:22:13Z",
    "busyness": 81,
    "low": 62,
    "high": 99,
    "rush_hour": true,
    "confidence": "medium"
  },
  {
    "time": "2026-01-24T19:22:13Z",
    "busyness": 69,
    "low": 50,
    "high": 87,
    "rush_hour": false,
    "confidence": "medium"
  },
  {
    "time": "2026-01-24T20:22:13Z",
    "busyness": 69,
    "low": 50,
    "high": 87,
    "rush_hour": false,
    "confidence": "medium"
  },
  {
    "time": "2026-01-24T21:22:13Z",
    "busyness": 69,
    "low": 50,
    "high": 87,
    "rush_hour": false,
    "confidence": "medium"
  },
  {
    "time": "2026-01-24T22:22:13Z",
    "busyness": 69,
    "low": 50,
    "high": 87,
    "rush_hour": false,
    "confidence": "medium"
  },
  {
    "time": "2026-01-24T23:22:13Z",
    "busyness": 69,
    "low": 50,
    "high": 87,
    "rush_hour": false,
    "confidence": "medium"
  },
  {
    "time": "2026-01-25T00:22:13Z",
    "busyness": 69,
    "low": 50,
    "high": 87,
    "rush_hour": false,
    "confidence": "medium"
  }
]