[
  {
    "time": "2025-12-21T09:18:41.840809Z",
    "busyness": 67,
    "low": 54,
    "high": 80,
    "rush_hour": true,
    "confidence": "medium"
  },
  {
    "time": "2025-12-21T10:18:41.840809Z",
    "busyness": 55,
    "low": 42,
    "high": 68,
    "rush_hour": false,
    "confidence": "medium"
  },
  {
    "time": "2025-12-21T11:18:41.840809Z",
    "busyness": 55,
    "low": 42,
    "high": 68,
    "rush_hour": false,
    "confidence": "medium"
  },
  {
    "time": "2025-12-21T12:18:41.840809Z",
    "busyness": 55,
    "low": 42,
    "high": 68,
    "rush_hour": false,
    "confidence": "medium"
  },
  {
    "time": "2025-12-21T13:18:41.840809Z",
    "busyness": 55,
    "low": 42,
    "high": 68,
    "rush_hour": false,
    "confidence": "medium"
  },
  {
    "time": "2025-12-21T14:18:41.840809Z",
    "busyness": 55,
    "low": 42,
    "high": 68,
    "rush_hour": false,
    "confidence": "medium"
  },
  {
    "time": "2025-12-21T15:18:41.840809Z",
    "busyness": 55,
    "low": 42,
    "high": 68,
    "rush_hour": false,
    "confidence": "medium"
  },
  {
    "time": "2025-12-21T16:18:41.840809Z",
    "busyness": 67,
    "low": 54,
    "high": 80,
    "rush_hour": true,
    "confidence": "medium"
  },
  {
    "time": "2025-12-21T17:18:41.840809Z",
    "busyness": 67,
    "low": 54,
    "high": 80,
    "rush_hour": true,
    "confidence": "medium"
  },
  {
    "time": "2025-12-21T18:18:41.840809Z",
    "busyness": 67,
    "low": 54,
    "high": 80,
    "rush_hour": true,
    "confidence": "medium"
  },
  {
    "time": "2025-12-21T19:18:41.840809Z",
    "busyness": 55,
    "low": 42,
    "high": 68,
    "rush_hour": false,
    "confidence": "medium"
  },
  {
    "time": "2025-12-21T20:18:41.840809Z",
    "busyness": 55,
    "low": 42,
    "high": 68,
    "rush_hour": false,
    "confidence": "medium"
  }
]