[
  {
    "time": "2026-01-05T02:04:54Z",
    "busyness": 76,
    "low": 56,
    "high": 96,
    "rush_hour": false,
    "confidence": "medium"
  },
  {
    "time": "2026-01-05T03:04:54Z",
    "busyness": 76,
    "low": 56,
    "high": 96,
    "rush_hour": false,
    "confidence": "medium"
  },
  {
    "time": "2026-01-05T04:04:54Z",
    "busyness": 76,
    "low": 56,
    "high": 96,
    "rush_hour": false,
    "confidence": "medium"
  },
  {
    "time": "2026-01-05T05:04:54Z",
    "busyness": 76,
    "low": 56,
    "high": 96,
    "rush_hour": false,
    "confidence": "medium"
  },
  {
    "time": "2026-01-05T06:04:54Z",
    "busyness": 76,
    "low": 56,
    "high": 96,
    "rush_hour": false,
    "confidence": "medium"
  },
  {
    "time": "2026-01-05T07:04:54Z",
    "busyness": 88,
    "low": 68,
    "high": 100,
    "rush_hour": true,
    "confidence": "medium"
  },
  {
    "time": "2026-01-05T08:04:54Z",
    "busyness": 88,
    "low": 68,
    "high": 100,
    "rush_hour": true,
    "confidence": "medium"
  },
  {
    "time": "2026-01-05T09:04:54Z",
    "busyness": 88,
    "low": 68,
    "high": 100,
    "rush_hour": true,
    "confidence": "medium"
  },
  {
    "time": "2026-01-05T10:04:54Z",
    "busyness": 76,
    "low": 56,
    "high": 96,
    "rush_hour": false,
    "confidence": "medium"
  },
  {
    "time": "2026-01-05T11:04:54Z",
    "busyness": 76,
    "low": 56,
    "high": 96,
    "rush_hour": false,
    "confidence": "medium"
  },
  {
    "time": "2026-01-05T12:04:54Z",
    "busyness": 76,
    "low": 56,
    "high": 96,
    "rush_hour": false,
    "confidence": "medium"
  },
  {
    "time": "2026-01-05T13:04:54Z",
    "busyness": 76,
    "low": 56,
    "high": 96,
    "rush_hour": false,
    "confidence": "medium"
  }
]