[
  {
    "time": "2026-06-30T17:15:02Z",
    "busyness": 93,
    "low": 75,
    "high": 100,
    "rush_hour": true,
    "confidence": "medium"
  },
  {
    "time": "2026-06-30T18:15:02Z",
    "busyness": 93,
    "low": 75,
    "high": 100,
    "rush_hour": true,
    "confidence": "medium"
  },
  {
    "time": "2026-06-30T19:15:02Z",
    "busyness": 81,
    "low": 63,
    "high": 99,
    "rush_hour": false,
    "confidence": "medium"
  },
  {
    "time": "2026-06-30T20:15:02Z",
    "busyness": 81,
    "low": 63,
    "high": 99,
    "rush_hour": false,
    "confidence": "medium"
  },
  {
    "time": "2026-06-30T21:15:02Z",
    "busyness": 81,
    "low": 63,
    "high": 99,
    "rush_hour": false,
    "confidence": "medium"
  },
  {
    "time": "2026-06-30T22:15:02Z",
    "busyness": 81,
    "low": 63,
    "high": 99,
    "rush_hour": false,
    "confidence": "medium"
  },
  {
    "time": "2026-06-30T23:15:02Z",
    "busyness": 81,
    "low": 63,
    "high": 99,
    "rush_hour": false,
    "confidence": "medium"
  },
  {
    "time": "2026-07-01T00:15:02Z",
    "busyness": 81,
    "low": 63,
    "high": 99,
    "rush_hour": false,
    "confidence": "medium"
  },
  {
    "time": "2026-07-01T01:15:02Z",
    "busyness": 81,
    "low": 63,
    "high": 99,
    "rush_hour": false,
    "confidence": "medium"
  },
  {
    "time": "2026-07-01T02:15:02Z",
    "busyness": 81,
    "low": 63,
    "high": 99,
    "rush_hour": false,
    "confidence": "medium"
  },
  {
    "time": "2026-07-01T03:15:02Z",
    "busyness": 81,
    "low": 63,
    "high": 99,
    "rush_hour": false,
    "confidence": "medium"
  },
  {
    "time": "2026-07-01T04:15:02Z",
    "busyness": 81,
    "low": 63,
    "high": 99,
    "rush_hour": false,
    "confidence": "medium"
  }
]