[
  {
    "time": "2026-02-03T07:38:13Z",
    "busyness": 77,
    "low": 57,
    "high": 97,
    "rush_hour": true,
    "confidence": "medium"
  },
  {
    "time": "2026-02-03T08:38:13Z",
    "busyness": 77,
    "low": 57,
    "high": 97,
    "rush_hour": true,
    "confidence": "medium"
  },
  {
    "time": "2026-02-03T09:38:13Z",
    "busyness": 77,
    "low": 57,
    "high": 97,
    "rush_hour": true,
    "confidence": "medium"
  },
  {
    "time": "2026-02-03T10:38:13Z",
    "busyness": 65,
    "low": 45,
    "high": 85,
    "rush_hour": false,
    "confidence": "medium"
  },
  {
    "time": "2026-02-03T11:38:13Z",
    "busyness": 65,
    "low": 45,
    "high": 85,
    "rush_hour": false,
    "confidence": "medium"
  },
  {
    "time": "2026-02-03T12:38:13Z",
    "busyness": 65,
    "low": 45,
    "high": 85,
    "rush_hour": false,
    "confidence": "medium"
  },
  {
    "time": "2026-02-03T13:38:13Z",
    "busyness": 65,
    "low": 45,
    "high": 85,
    "rush_hour": false,
    "confidence": "medium"
  },
  {
    "time": "2026-02-03T14:38:13Z",
    "busyness": 65,
    "low": 45,
    "high": 85,
    "rush_hour": false,
    "confidence": "medium"
  },
  {
    "time": "2026-02-03T15:38:13Z",
    "busyness": 65,
    "low": 45,
    "high": 85,
    "rush_hour": false,
    "confidence": "medium"
  },
  {
    "time": "2026-02-03T16:38:13Z",
    "busyness": 77,
    "low": 57,
    "high": 97,
    "rush_hour": true,
    "confidence": "medium"
  },
  {
    "time": "2026-02-03T17:38:13Z",
    "busyness": 77,
    "low": 57,
    "high": 97,
    "rush_hour": true,
    "confidence": "medium"
  },
  {
    "time": "2026-02-03T18:38:13Z",
    "busyness": 77,
    "low": 57,
    "high": 97,
    "rush_hour": true,
    "confidence": "medium"
  }
]