[
  {
    "time": "2026-04-04T14:44:54Z",
    "busyness": 73,
    "low": 52,
    "high": 93,
    "rush_hour": false,
    "confidence": "medium"
  },
  {
    "time": "2026-04-04T15:44:54Z",
    "busyness": 73,
    "low": 52,
    "high": 93,
    "rush_hour": false,
    "confidence": "medium"
  },
  {
    "time": "2026-04-04T16:44:54Z",
    "busyness": 85,
    "low": 64,
    "high": 100,
    "rush_hour": true,
    "confidence": "medium"
  },
  {
    "time": "2026-04-04T17:44:54Z",
    "busyness": 85,
    "low": 64,
    "high": 100,
    "rush_hour": true,
    "confidence": "medium"
  },
  {
    "time": "2026-04-04T18:44:54Z",
    "busyness": 85,
    "low": 64,
    "high": 100,
    "rush_hour": true,
    "confidence": "medium"
  },
  {
    "time": "2026-04-04T19:44:54Z",
    "busyness": 73,
    "low": 52,
    "high": 93,
    "rush_hour": false,
    "confidence": "medium"
  },
  {
    "time": "2026-04-04T20:44:54Z",
    "busyness": 73,
    "low": 52,
    "high": 93,
    "rush_hour": false,
    "confidence": "medium"
  },
  {
    "time": "2026-04-04T21:44:54Z",
    "busyness": 73,
    "low": 52,
    "high": 93,
    "rush_hour": false,
    "confidence": "medium"
  },
  {
    "time": "2026-04-04T22:44:54Z",
    "busyness": 73,
    "low": 52,
    "high": 93,
    "rush_hour": false,
    "confidence": "medium"
  },
  {
    "time": "2026-04-04T23:44:54Z",
    "busyness": 73,
    "low": 52,
    "high": 93,
    "rush_hour": false,
    "confidence": "medium"
  },
  {
    "time": "2026-04-05T00:44:54Z",
    "busyness": 73,
    "low": 52,
    "high": 93,
    "rush_hour": false,
    "confidence": "medium"
  },
  {
    "time": "2026-04-05T01:44:54Z",
    "busyness": 73,
    "low": 52,
    "high": 93,
    "rush_hour": false,
    "confidence": "medium"
  }
]