[
  {
    "time": "2026-03-05T08:35:39Z",
    "busyness": 81,
    "low": 62,
    "high": 100,
    "rush_hour": true,
    "confidence": "medium"
  },
  {
    "time": "2026-03-05T09:35:39Z",
    "busyness": 81,
    "low": 62,
    "high": 100,
    "rush_hour": true,
    "confidence": "medium"
  },
  {
    "time": "2026-03-05T10:35:39Z",
    "busyness": 69,
    "low": 50,
    "high": 89,
    "rush_hour": false,
    "confidence": "medium"
  },
  {
    "time": "2026-03-05T11:35:39Z",
    "busyness": 69,
    "low": 50,
    "high": 89,
    "rush_hour": false,
    "confidence": "medium"
  },
  {
    "time": "2026-03-05T12:35:39Z",
    "busyness": 69,
    "low": 50,
    "high": 89,
    "rush_hour": false,
    "confidence": "medium"
  },
  {
    "time": "2026-03-05T13:35:39Z",
    "busyness": 69,
    "low": 50,
    "high": 89,
    "rush_hour": false,
    "confidence": "medium"
  },
  {
    "time": "2026-03-05T14:35:39Z",
    "busyness": 69,
    "low": 50,
    "high": 89,
    "rush_hour": false,
    "confidence": "medium"
  },
  {
    "time": "2026-03-05T15:35:39Z",
    "busyness": 69,
    "low": 50,
    "high": 89,
    "rush_hour": false,
    "confidence": "medium"
  },
  {
    "time": "2026-03-05T16:35:39Z",
    "busyness": 81,
    "low": 62,
    "high": 100,
    "rush_hour": true,
    "confidence": "medium"
  },
  {
    "time": "2026-03-05T17:35:39Z",
    "busyness": 81,
    "low": 62,
    "high": 100,
    "rush_hour": true,
    "confidence": "medium"
  },
  {
    "time": "2026-03-05T18:35:39Z",
    "busyness": 81,
    "low": 62,
    "high": 100,
    "rush_hour": true,
    "confidence": "medium"
  },
  {
    "time": "2026-03-05T19:35:39Z",
    "busyness": 69,
    "low": 50,
    "high": 89,
    "rush_hour": false,
    "confidence": "medium"
  }
]