[
  {
    "time": "2026-06-23T22:23:24Z",
    "busyness": 79,
    "low": 61,
    "high": 97,
    "rush_hour": false,
    "confidence": "medium"
  },
  {
    "time": "2026-06-23T23:23:24Z",
    "busyness": 79,
    "low": 61,
    "high": 97,
    "rush_hour": false,
    "confidence": "medium"
  },
  {
    "time": "2026-06-24T00:23:24Z",
    "busyness": 79,
    "low": 61,
    "high": 97,
    "rush_hour": false,
    "confidence": "medium"
  },
  {
    "time": "2026-06-24T01:23:24Z",
    "busyness": 79,
    "low": 61,
    "high": 97,
    "rush_hour": false,
    "confidence": "medium"
  },
  {
    "time": "2026-06-24T02:23:24Z",
    "busyness": 79,
    "low": 61,
    "high": 97,
    "rush_hour": false,
    "confidence": "medium"
  },
  {
    "time": "2026-06-24T03:23:24Z",
    "busyness": 79,
    "low": 61,
    "high": 97,
    "rush_hour": false,
    "confidence": "medium"
  },
  {
    "time": "2026-06-24T04:23:24Z",
    "busyness": 79,
    "low": 61,
    "high": 97,
    "rush_hour": false,
    "confidence": "medium"
  },
  {
    "time": "2026-06-24T05:23:24Z",
    "busyness": 79,
    "low": 61,
    "high": 97,
    "rush_hour": false,
    "confidence": "medium"
  },
  {
    "time": "2026-06-24T06:23:24Z",
    "busyness": 79,
    "low": 61,
    "high": 97,
    "rush_hour": false,
    "confidence": "medium"
  },
  {
    "time": "2026-06-24T07:23:24Z",
    "busyness": 91,
    "low": 73,
    "high": 100,
    "rush_hour": true,
    "confidence": "medium"
  },
  {
    "time": "2026-06-24T08:23:24Z",
    "busyness": 91,
    "low": 73,
    "high": 100,
    "rush_hour": true,
    "confidence": "medium"
  },
  {
    "time": "2026-06-24T09:23:24Z",
    "busyness": 91,
    "low": 73,
    "high": 100,
    "rush_hour": true,
    "confidence": "medium"
  }
]