[
  {
    "time": "2026-03-27T09:39:47Z",
    "busyness": 83,
    "low": 63,
    "high": 100,
    "rush_hour": true,
    "confidence": "medium"
  },
  {
    "time": "2026-03-27T10:39:47Z",
    "busyness": 71,
    "low": 51,
    "high": 92,
    "rush_hour": false,
    "confidence": "medium"
  },
  {
    "time": "2026-03-27T11:39:47Z",
    "busyness": 71,
    "low": 51,
    "high": 92,
    "rush_hour": false,
    "confidence": "medium"
  },
  {
    "time": "2026-03-27T12:39:47Z",
    "busyness": 71,
    "low": 51,
    "high": 92,
    "rush_hour": false,
    "confidence": "medium"
  },
  {
    "time": "2026-03-27T13:39:47Z",
    "busyness": 71,
    "low": 51,
    "high": 92,
    "rush_hour": false,
    "confidence": "medium"
  },
  {
    "time": "2026-03-27T14:39:47Z",
    "busyness": 71,
    "low": 51,
    "high": 92,
    "rush_hour": false,
    "confidence": "medium"
  },
  {
    "time": "2026-03-27T15:39:47Z",
    "busyness": 71,
    "low": 51,
    "high": 92,
    "rush_hour": false,
    "confidence": "medium"
  },
  {
    "time": "2026-03-27T16:39:47Z",
    "busyness": 83,
    "low": 63,
    "high": 100,
    "rush_hour": true,
    "confidence": "medium"
  },
  {
    "time": "2026-03-27T17:39:47Z",
    "busyness": 83,
    "low": 63,
    "high": 100,
    "rush_hour": true,
    "confidence": "medium"
  },
  {
    "time": "2026-03-27T18:39:47Z",
    "busyness": 83,
    "low": 63,
    "high": 100,
    "rush_hour": true,
    "confidence": "medium"
  },
  {
    "time": "2026-03-27T19:39:47Z",
    "busyness": 71,
    "low": 51,
    "high": 92,
    "rush_hour": false,
    "confidence": "medium"
  },
  {
    "time": "2026-03-27T20:39:47Z",
    "busyness": 71,
    "low": 51,
    "high": 92,
    "rush_hour": false,
    "confidence": "medium"
  }
]