{
  "timestamp": "2026-03-12T01:05:02Z",
  "context": {
    "holiday_phase": "normal",
    "date": "2026-03-12",
    "hour": 1
  },
  "weather": {
    "temperature_C": 6.47,
    "windspeed_kmh": 4.59,
    "condition": "Clouds"
  },
  "tfl": [
    {
      "name": "Bakerloo",
      "mode": "tube",
      "status": "Minor Delays"
    },
    {
      "name": "Central",
      "mode": "tube",
      "status": "Minor Delays"
    },
    {
      "name": "Circle",
      "mode": "tube",
      "status": "Minor Delays"
    },
    {
      "name": "District",
      "mode": "tube",
      "status": "Severe Delays"
    },
    {
      "name": "DLR",
      "mode": "dlr",
      "status": "Good Service"
    },
    {
      "name": "Hammersmith & City",
      "mode": "tube",
      "status": "Severe Delays"
    },
    {
      "name": "Jubilee",
      "mode": "tube",
      "status": "Good Service"
    },
    {
      "name": "Liberty",
      "mode": "overground",
      "status": "Good Service"
    },
    {
      "name": "Lioness",
      "mode": "overground",
      "status": "Good Service"
    },
    {
      "name": "Metropolitan",
      "mode": "tube",
      "status": "Good Service"
    },
    {
      "name": "Mildmay",
      "mode": "overground",
      "status": "Good Service"
    },
    {
      "name": "Northern",
      "mode": "tube",
      "status": "Part Closure"
    },
    {
      "name": "Piccadilly",
      "mode": "tube",
      "status": "Good Service"
    },
    {
      "name": "Suffragette",
      "mode": "overground",
      "status": "Good Service"
    },
    {
      "name": "Victoria",
      "mode": "tube",
      "status": "Good Service"
    },
    {
      "name": "Waterloo & City",
      "mode": "tube",
      "status": "Service Closed"
    },
    {
      "name": "Weaver",
      "mode": "overground",
      "status": "Good Service"
    },
    {
      "name": "Windrush",
      "mode": "overground",
      "status": "Good Service"
    }
  ],
  "events": [],
  "venues": [],
  "clusters": {
    "transit": 96,
    "leisure": 35,
    "dining": 30
  },
  "transit_pressure": {
    "score": 96,
    "level": "High",
    "drivers": [
      "7 disrupted lines"
    ]
  }
}