{
  "total_anomalies": 500,
  "date_range": {
    "start": "2026-04-23T13:00:39+00:00",
    "end": "2026-07-16T09:55:56+00:00"
  },
  "by_type": {
    "volatile_demand": 361,
    "prolonged_peak": 123,
    "suppressed_demand": 16
  },
  "by_severity": {
    "low": 361,
    "medium": 139
  },
  "by_persistence": {
    "established": 390,
    "transient": 57,
    "emerging": 53
  },
  "peak_hours": {
    "6": 35,
    "10": 33,
    "20": 32,
    "2": 32,
    "19": 29,
    "13": 28
  },
  "top_drivers": {
    "fair_weather": 479,
    "transport_disruption": 421
  },
  "confidence_stats": {
    "avg": 0.596,
    "min": 0.45,
    "max": 0.86
  },
  "interpretation": {
    "dominant_anomaly": "volatile_demand",
    "most_common_driver": "fair_weather",
    "most_unstable_hours": [
      6,
      10,
      20
    ],
    "data_quality_note": "Confidence reflects signal agreement, not ground truth. Seasonal period shows elevated volatility compared to normal weeks."
  }
}